megasepryte/__init__.py
megasepryte/megasepryte.py
megasepryte-1.0.9.dist-info/METADATA
megasepryte-1.0.9.dist-info/WHEEL
megasepryte-1.0.9.dist-info/licenses/LICENSE
megasepryte-1.0.9.dist-info/RECORD
