Metadata-Version: 2.1
Name: megasepryte
Version: 1.0.9
Summary: Aseprite to megadrive compatible assembly
Author-email: Trygve Leergaard <atleergaard2@hotmail.com>
License-File: LICENSE
Classifier: License :: OSI Approved :: MIT License
Classifier: Operating System :: OS Independent
Classifier: Programming Language :: Python :: 3
Requires-Python: >=3.10
